deterrersapi
