Metadata-Version: 2.1
Name: deterrers-api
Version: 0.2
Summary: Python API client for DETERRERS
Home-page: https://github.com/virtUOS/deterrers-api
Author: Lars Kiesow
Author-email: lkiesow@uos.de
License: MIT
Platform: UNKNOWN
